[
    {
        "key": "dbln",
        "value": "%7B%22100090876384136%22%3A%22eIZNXX4L%22%2C%22100012326474276%22%3A%22fqJ3uwvZ%22%7D",
        "domain": "facebook.com",
        "path": "/login/device-based/",
        "hostOnly": false,
        "creation": "2024-09-26T01:16:26.020Z",
        "lastAccessed": "2024-09-26T01:16:26.020Z"
    },
    {
        "key": "datr",
        "value": "t9XzZuXugSEMCMYNmphLSW16",
        "domain": "facebook.com",
        "path": "/",
        "hostOnly": false,
        "creation": "2024-09-26T01:16:26.020Z",
        "lastAccessed": "2024-09-26T01:16:26.020Z"
    },
    {
        "key": "sb",
        "value": "t9XzZhccsUZ4bvdvEKPs1w3h",
        "domain": "facebook.com",
        "path": "/",
        "hostOnly": false,
        "creation": "2024-09-26T01:16:26.020Z",
        "lastAccessed": "2024-09-26T01:16:26.020Z"
    },
    {
        "key": "ps_l",
        "value": "1",
        "domain": "facebook.com",
        "path": "/",
        "hostOnly": false,
        "creation": "2024-09-26T01:16:26.020Z",
        "lastAccessed": "2024-09-26T01:16:26.020Z"
    },
    {
        "key": "ps_n",
        "value": "1",
        "domain": "facebook.com",
        "path": "/",
        "hostOnly": false,
        "creation": "2024-09-26T01:16:26.020Z",
        "lastAccessed": "2024-09-26T01:16:26.020Z"
    },
    {
        "key": "vpd",
        "value": "v1%3B767x393x2.75",
        "domain": "facebook.com",
        "path": "/",
        "hostOnly": false,
        "creation": "2024-09-26T01:16:26.020Z",
        "lastAccessed": "2024-09-26T01:16:26.020Z"
    },
    {
        "key": "m_pixel_ratio",
        "value": "2.75",
        "domain": "facebook.com",
        "path": "/",
        "hostOnly": false,
        "creation": "2024-09-26T01:16:26.020Z",
        "lastAccessed": "2024-09-26T01:16:26.020Z"
    },
    {
        "key": "wd",
        "value": "393x767",
        "domain": "facebook.com",
        "path": "/",
        "hostOnly": false,
        "creation": "2024-09-26T01:16:26.020Z",
        "lastAccessed": "2024-09-26T01:16:26.020Z"
    },
    {
        "key": "c_user",
        "value": "100012326474276",
        "domain": "facebook.com",
        "path": "/",
        "hostOnly": false,
        "creation": "2024-09-26T01:16:26.020Z",
        "lastAccessed": "2024-09-26T01:16:26.020Z"
    },
    {
        "key": "fr",
        "value": "0DHvZ0NETLf4tIbiQ.AWWGll6nO1mM2aQnw34CLjRj7n8.Bm89W3..AAA.0.0.Bm9LRf.AWUjbK7u2H8",
        "domain": "facebook.com",
        "path": "/",
        "hostOnly": false,
        "creation": "2024-09-26T01:16:26.020Z",
        "lastAccessed": "2024-09-26T01:16:26.020Z"
    },
    {
        "key": "xs",
        "value": "28%3A5z7txCmzwGvYFg%3A2%3A1727312992%3A-1%3A5244",
        "domain": "facebook.com",
        "path": "/",
        "hostOnly": false,
        "creation": "2024-09-26T01:16:26.020Z",
        "lastAccessed": "2024-09-26T01:16:26.020Z"
    },
    {
        "key": "locale",
        "value": "en_GB",
        "domain": "facebook.com",
        "path": "/",
        "hostOnly": false,
        "creation": "2024-09-26T01:16:26.020Z",
        "lastAccessed": "2024-09-26T01:16:26.020Z"
    },
    {
        "key": "fbl_st",
        "value": "100421521%3BT%3A28788550",
        "domain": "facebook.com",
        "path": "/",
        "hostOnly": false,
        "creation": "2024-09-26T01:16:26.020Z",
        "lastAccessed": "2024-09-26T01:16:26.020Z"
    },
    {
        "key": "wl_cbv",
        "value": "v2%3Bclient_version%3A2630%3Btimestamp%3A1727312997%3BCRCM%3A-1086680871",
        "domain": "facebook.com",
        "path": "/",
        "hostOnly": false,
        "creation": "2024-09-26T01:16:26.020Z",
        "lastAccessed": "2024-09-26T01:16:26.020Z"
    }
]
